vsql/__init__.py
vsql/embedders/openai.py
vsql/embedders/st.py
vsql/relational_dbs/postgres/__init__.py
vsql/relational_dbs/sqlite/__init__.py
vsql/vector_dbs/faiss.py
vsql/vector_dbs/pinecone.py
vsql-0.1.2.dist-info/METADATA
vsql-0.1.2.dist-info/WHEEL
vsql-0.1.2.dist-info/RECORD
